Workbook

Sheet Dashboard
B2: PURC Letter & Document Tracking System
B3: Executive Dashboard · Energy Sector Correspondence Register
B6: TOTAL LETTERS | D6: TOTAL RECEIVED | F6: TOTAL DISPATCHED
B7: =COUNT('Received Register'!$A$5:$A$200)+COUNT('Dispatched Register'!$A$5:$A$200) | D7: =COUNT('Received Register'!$A$5:$A$200) | F7: =COUNT('Dispatched Register'!$A$5:$A$200)
B10: URGENT LETTERS | D10: NORMAL LETTERS | F10: DIRECTORATES
B11: =COUNTIF('Received Register'!$I$5:$I$200,"Urgent")+COUNTIF('Dispatched Register'!$G$5:$G$200,"Urgent") | D11: =COUNTIF('Received Register'!$I$5:$I$200,"Normal")+COUNTIF('Dispatched Register'!$G$5:$G$200,"Normal") | F11: =COUNTA(Reference!$A$2:$A$8)
B14: Directorate Workload
B15: Directorate | C15: Received | D15: Dispatched | E15: Total
B16: =Analytics!A11 | C16: =Analytics!B11 | D16: =Analytics!C11 | E16: =Analytics!D11
B17: =Analytics!A12 | C17: =Analytics!B12 | D17: =Analytics!C12 | E17: =Analytics!D12
B18: =Analytics!A13 | C18: =Analytics!B13 | D18: =Analytics!C13 | E18: =Analytics!D13
B19: =Analytics!A14 | C19: =Analytics!B14 | D19: =Analytics!C14 | E19: =Analytics!D14
B20: =Analytics!A15 | C20: =Analytics!B15 | D20: =Analytics!C15 | E20: =Analytics!D15
B21: =Analytics!A16 | C21: =Analytics!B16 | D21: =Analytics!C16 | E21: =Analytics!D16
B22: =Analytics!A17 | C22: =Analytics!B17 | D22: =Analytics!C17 | E22: =Analytics!D17
B24: Figures update automatically from the Received & Dispatched registers. Green cells are links to other sheets.

Sheet Received Register
A1: Received Letter Register
A2: Public Utilities Regulatory Commission · Executive Secretariat, Energy Sector
A4: Registry No | B4: Letter Date | C4: Reference No | D4: Sender Institution | E4: From (Signatory) | F4: Received By | G4: Subject | H4: Directorate | I4: Priority | J4: Status | K4: Remarks
A5: 1 | B5: 46116 | C5: 1 | D5: Electricity Company of Ghana | E5: Managing Director, Electricity Company of Ghana | F5: Cecil Oduro Nyarko | G5: Request for Data on Electricity Cost | H5: Energy Services and Performance Monitoring | I5: Normal | J5: Received | K5: Received at ES through Natasha, Front Desk. Not yet dispatched.
A6: 2 | B6: 46119 | C6: 2 | D6: Northern Electricity Distribution Company | E6: Northern Electricity Distribution Company | F6: Executive Secretary | G6: Request for clarification on 2026 tariff adjustment | H6: Regulatory Economics | I6: Urgent | J6: Received | K6: Dispatched from ES to Regulatory Economics for tariff review.
A7: 3 | B7: 46123 | C7: 3 | D7: Ghana Water Company Limited | E7: Ghana Water Company Limited | F7: Executive Secretary | G7: Submission of water quality monitoring returns | H7: Water Services and Performance Monitoring | I7: Normal | J7: Received | K7: Dispatched from ES to Water Services and Performance Monitoring. Received by department on April 12, 2026.
A8: 4 | B8: 46128 | C8: 4 | D8: Northern Region Consumer Group | E8: Northern Region Consumer Group | F8: Executive Secretary | G8: Consumer petition on estimated billing in Tamale | H8: Regional Operations | I8: Urgent | J8: Received | K8: Urgent petition dispatched from ES to Regional Operations for regional follow-up.
A9: 5 | B9: 46133 | C9: 5 | D9: Association of Independent Power Producers | E9: Association of Independent Power Producers | F9: Executive Secretary | G9: Request for legal opinion on licence condition | H9: Legal Services | I9: Urgent | J9: Received | K9: Received at ES office and awaiting dispatch to Legal Services.
A10: 6 | B10: 46139 | C10: 6 | D10: BlueGate Conference Services | E10: BlueGate Conference Services | F10: Executive Secretary | G10: Invoice submission for stakeholder workshop logistics | H10: Finance and Administration | I10: Normal | J10: Received | K10: Dispatched from ES to Finance and Administration for payment verification.
A11: 7 | B11: 46146 | C11: 7 | D11: Ghana Grid Company Limited | E11: Ghana Grid Company Limited | F11: Energy Services and Performance Monitoring | G11: Quarterly electricity reliability performance report | H11: Energy Services and Performance Monitoring | I11: Normal | J11: Received | K11: Dispatched from ES to ESPM. Received by department for technical review.
A12: 8 | B12: 46150 | C12: 8 | D12: Community Water and Sanitation Agency | E12: Community Water and Sanitation Agency | F12: Executive Secretary | G12: Water service interruption report for Nsawam | H12: Water Services and Performance Monitoring | I12: Urgent | J12: Received | K12: Dispatched from ES to Water Services and Performance Monitoring for service quality review.
A13: 9 | B13: 46153 | C13: 9 | D13: Ghana National Gas Company | E13: Ghana National Gas Company | F13: Executive Secretary | G13: Natural gas cost data for tariff computation | H13: Regulatory Economics | I13: Normal | J13: Received | K13: Dispatched from ES to Regulatory Economics. Received by department for tariff model update.
A14: 10 | B14: 46157 | C14: 10 | D14: Electricity Company of Ghana | E14: Electricity Company of Ghana | F14: Executive Secretary | G14: Urgent notice on transformer overload at Pokuase | H14: Energy Services and Performance Monitoring | I14: Urgent | J14: Received | K14: Urgent technical letter dispatched from ES to ESPM for immediate monitoring action.
A15: 11 | B15: 46161 | C15: 11 | D15: PURC Ashanti Regional Office | E15: PURC Ashanti Regional Office | F15: Executive Secretary | G15: Regional office request for complaint mediation support | H15: Regional Operations | I15: Normal | J15: Received | K15: Received at ES office. Not yet dispatched to Regional Operations.
A16: 12 | B16: 46164 | C16: 12 | D16: Public Affairs Unit | E16: Public Affairs Unit | F16: Executive Secretary | G16: Budget request for public education campaign | H16: Finance and Administration | I16: Normal | J16: Received | K16: Dispatched from ES to Finance and Administration for budget advice.
... A19: 15 | B19: 46174 | C19: 15 | D19: Northern Electricity Distribution Company | E19: Northern Electricity Distribution Company | F19: Executive Secretary | G19: Monthly power outage schedule notification | H19: Energy Services and Performance Monitoring | I19: Normal | J19: Received | K19: Dispatched from ES to ESPM for monitoring and record update.

Sheet Dispatched Register
A1: Dispatched Letter Register
A2: Public Utilities Regulatory Commission · Executive Secretariat, Energy Sector
A4: Registry No | B4: Dispatch Date | C4: Reference No | D4: Recipient Institution | E4: Responsible Directorate | F4: Subject | G4: Priority | H4: Status | I4: Remarks
A5: 16 | B5: 46117 | C5: 16 | D5: Electricity Company of Ghana | E5: Energy Services and Performance Monitoring | F5: Acknowledgement of electricity cost data request | G5: Normal | H5: Dispatched | I5: Dispatched from PURC to Electricity Company of Ghana and logged by ES.
A6: 17 | B6: 46122 | C6: 17 | D6: Northern Electricity Distribution Company | E6: Regulatory Economics | F6: Draft response on tariff adjustment clarification | G6: Urgent | H6: Dispatched | I6: Ready for ES signature before external dispatch to NEDCo.
A7: 18 | B7: 46127 | C7: 18 | D7: Ghana Water Company Limited | E7: Water Services and Performance Monitoring | F7: Request for corrected water quality dataset | G7: Normal | H7: Dispatched | I7: Dispatched from PURC to Ghana Water Company Limited for corrected returns.
A8: 19 | B8: 46132 | C8: 19 | D8: PURC Northern Regional Office | E8: Regional Operations | F8: Directive on estimated billing complaint investigation | G8: Urgent | H8: Dispatched | I8: Urgent outgoing letter dispatched from PURC to the Northern Regional Office.
A9: 20 | B9: 46137 | C9: 20 | D9: Association of Independent Power Producers | E9: Legal Services | F9: Legal review request for licence condition | G9: Normal | H9: Dispatched | I9: Ready for ES signature before dispatch to the Association of Independent Power Producers.
A10: 21 | B10: 46142 | C10: 21 | D10: BlueGate Conference Services | E10: Finance and Administration | F10: Payment processing acknowledgement | G10: Normal | H10: Dispatched | I10: Dispatched from PURC to vendor after Finance and Administration verification.
A11: 22 | B11: 46145 | C11: 22 | D11: Ghana Grid Company Limited | E11: Energy Services and Performance Monitoring | F11: Request for grid reliability supporting data | G11: Normal | H11: Dispatched | I11: Dispatched from PURC to Ghana Grid Company Limited for reliability data confirmation.
A12: 23 | B12: 46151 | C12: 23 | D12: Community Water and Sanitation Agency | E12: Water Services and Performance Monitoring | F12: Draft response on Nsawam water service interruption | G12: Urgent | H12: Dispatched | I12: Ready for ES signature before dispatch to Community Water and Sanitation Agency.
A13: 24 | B13: 46155 | C13: 24 | D13: Ghana National Gas Company | E13: Regulatory Economics | F13: Acknowledgement of natural gas tariff data | G13: Normal | H13: Dispatched | I13: Dispatched from PURC to Ghana National Gas Company after Regulatory Economics review.
A14: 25 | B14: 46158 | C14: 25 | D14: Electricity Company of Ghana | E14: Energy Services and Performance Monitoring | F14: Emergency monitoring request on Pokuase transformer overload | G14: Urgent | H14: Dispatched | I14: Urgent outgoing letter dispatched from PURC to ECG for immediate technical update.
A15: 26 | B15: 46162 | C15: 26 | D15: PURC Ashanti Regional Office | E15: Regional Operations | F15: Mediation support letter for Ashanti regional complaint | G15: Normal | H15: Dispatched | I15: Ready for ES signature before dispatch to PURC Ashanti Regional Office.
A16: 27 | B16: 46166 | C16: 27 | D16: Public Affairs Unit | E16: Finance and Administration | F16: Budget concurrence for public education campaign | G16: Normal | H16: Dispatched | I16: Dispatched from PURC to Public Affairs Unit after Finance and Administration advice.
... A19: 30 | B19: 46174 | C19: 30 | D19: Northern Electricity Distribution Company | E19: Energy Services and Performance Monitoring | F19: Acknowledgement of NEDCo power outage schedule | G19: Normal | H19: Dispatched | I19: Ready for ES signature before dispatch to NEDCo.

Sheet Analytics
A1: Analytics
A3: Letters by Month
A4: Month | B4: Received | C4: Dispatched
A5: Apr 2026 | B5: =COUNTIFS('Received Register'!$B$5:$B$200,">="&DATE(2026,4,1),'Received Register'!$B$5:$B$200,"<="&DATE(2026,4,30)) | C5: =COUNTIFS('Dispatched Register'!$B$5:$B$200,">="&DATE(2026,4,1),'Dispatched Register'!$B$5:$B$200,"<="&DATE(2026,4,30))
A6: May 2026 | B6: =COUNTIFS('Received Register'!$B$5:$B$200,">="&DATE(2026,5,1),'Received Register'!$B$5:$B$200,"<="&DATE(2026,5,31)) | C6: =COUNTIFS('Dispatched Register'!$B$5:$B$200,">="&DATE(2026,5,1),'Dispatched Register'!$B$5:$B$200,"<="&DATE(2026,5,31))
A7: Jun 2026 | B7: =COUNTIFS('Received Register'!$B$5:$B$200,">="&DATE(2026,6,1),'Received Register'!$B$5:$B$200,"<="&DATE(2026,6,30)) | C7: =COUNTIFS('Dispatched Register'!$B$5:$B$200,">="&DATE(2026,6,1),'Dispatched Register'!$B$5:$B$200,"<="&DATE(2026,6,30))
A9: Directorate Workload
A10: Directorate | B10: Received | C10: Dispatched | D10: Total
A11: Executive Secretary | B11: =COUNTIF('Received Register'!$H$5:$H$200,A11) | C11: =COUNTIF('Dispatched Register'!$E$5:$E$200,A11) | D11: =B11+C11
A12: Regulatory Economics | B12: =COUNTIF('Received Register'!$H$5:$H$200,A12) | C12: =COUNTIF('Dispatched Register'!$E$5:$E$200,A12) | D12: =B12+C12
A13: Energy Services and Performance Monitoring | B13: =COUNTIF('Received Register'!$H$5:$H$200,A13) | C13: =COUNTIF('Dispatched Register'!$E$5:$E$200,A13) | D13: =B13+C13
A14: Water Services and Performance Monitoring | B14: =COUNTIF('Received Register'!$H$5:$H$200,A14) | C14: =COUNTIF('Dispatched Register'!$E$5:$E$200,A14) | D14: =B14+C14
A15: Regional Operations | B15: =COUNTIF('Received Register'!$H$5:$H$200,A15) | C15: =COUNTIF('Dispatched Register'!$E$5:$E$200,A15) | D15: =B15+C15
A16: Legal Services | B16: =COUNTIF('Received Register'!$H$5:$H$200,A16) | C16: =COUNTIF('Dispatched Register'!$E$5:$E$200,A16) | D16: =B16+C16
A17: Finance and Administration | B17: =COUNTIF('Received Register'!$H$5:$H$200,A17) | C17: =COUNTIF('Dispatched Register'!$E$5:$E$200,A17) | D17: =B17+C17
A19: Priority Split
A20: Priority | B20: Count
A21: Normal | B21: =COUNTIF('Received Register'!$I$5:$I$200,"Normal")+COUNTIF('Dispatched Register'!$G$5:$G$200,"Normal")
A22: Urgent | B22: =COUNTIF('Received Register'!$I$5:$I$200,"Urgent")+COUNTIF('Dispatched Register'!$G$5:$G$200,"Urgent")

Sheet Reference
A1: Directorates | B1: Priorities | C1: Statuses | D1: Institutions
A2: Executive Secretary | B2: Normal | C2: Received | D2: Association of Independent Power Producers
A3: Regulatory Economics | B3: Urgent | C3: Dispatched | D3: BlueGate Conference Services
A4: Energy Services and Performance Monitoring | D4: Cape Coast Residents Association
A5: Water Services and Performance Monitoring | D5: Community Water and Sanitation Agency
A6: Regional Operations | D6: Electricity Company of Ghana
A7: Legal Services | D7: Ghana Grid Company Limited
A8: Finance and Administration | D8: Ghana National Gas Company
D9: Ghana Water Company Limited
D10: Ministry of Energy
D11: Northern Electricity Distribution Company
D12: Northern Region Consumer Group
D13: PURC Ashanti Regional Office
D14: PURC Northern Regional Office
D15: Public Affairs Unit
